AxNICCfg.dll
CLAllSerial_MD_VC120_v3_0.dll
CLAllSerial_MD_VC120_v3_0_MVS_v3_1_0.dll
CLAllSerial_MD_VC141_v3_1_Basler_pylon.dll
CLProtocol_MD_VC120_v3_0.dll
CLProtocol_MD_VC120_v3_0_MVS_v3_1_0.dll
CLProtocol_MD_VC141_v3_1_Basler_pylon.dll
CLSerCOM.dll
DxImageProc.dll
FirmwareUpdate_MD_VC141_v3_1_Basler_pylon.dll
FormatConversion.dll
GCBase_MD_VC120_v3_0.dll
GCBase_MD_VC120_v3_0_MVS_v3_1_0.dll
GCBase_MD_VC141_v3_1_Basler_pylon.dll
GenApi_MD_VC120_v3_0.dll
GenApi_MD_VC120_v3_0_MVS_v3_1_0.dll
GenApi_MD_VC141_v3_1_Basler_pylon.dll
GenCP_MD_VC120_v3_0.dll
GxIAPI.dll
GxIAPICPP.dll
GxIAPICPPEx.dll
Log_MD_VC120_v3_0.dll
Log_MD_VC120_v3_0_MVS_v3_1_0.dll
Log_MD_VC141_v3_1_Basler_pylon.dll
MVGenICamConfig_v6_2.dll
MVGigEVisionSDK.dll
MathParser_MD_VC120_v3_0.dll
MathParser_MD_VC120_v3_0_MVS_v3_1_0.dll
MathParser_MD_VC141_v3_1_Basler_pylon.dll
MediaProcess.dll
MvCamLVision.dll
MvCameraControl.dll
MvCameraControlWrapper.dll
MvRender.dll
MvUsb3vTL.dll
NodeMapData_MD_VC120_v3_0.dll
NodeMapData_MD_VC120_v3_0_MVS_v3_1_0.dll
NodeMapData_MD_VC141_v3_1_Basler_pylon.dll
PyRVC.cp37-win_amd64.pyd
PylonBase_v6_2.dll
PylonCLSer_v6_2_TL.dll
PylonC_v6_2.dll
PylonCamEmu_v6_2_TL.dll
PylonGUI_v6_2.dll
PylonGigE_v6_2_TL.dll
PylonGtc_v6_2_TL.dll
PylonUsb_v6_2_TL.dll
PylonUtility_v6_2.dll
RVC.dll
XmlParser_MD_VC120_v3_0.dll
XmlParser_MD_VC120_v3_0_MVS_v3_1_0.dll
XmlParser_MD_VC141_v3_1_Basler_pylon.dll
avcodec-57.dll
avdevice-57.dll
avfilter-6.dll
avformat-57.dll
avutil-55.dll
gxapi_v13.dll
libbz2.dll
libmmd.dll
libpng16.dll
log4cpp_MD_VC120_v3_0.dll
log4cpp_MD_VC120_v3_0_MVS_v3_1_0.dll
log4cpp_MD_VC141_v3_1_Basler_pylon.dll
mfc90.dll
msvcm90.dll
msvcp100.dll
msvcp120.dll
msvcp90.dll
msvcr100.dll
msvcr120.dll
msvcr90.dll
pthreadGC2.dll
pthreadVC2.dll
swscale-4.dll
uxapi_v12.dll
uxtopapi_v6_2.dll
vcruntime140_1.dll
zlib.dll
test_PyRVC2-1.8.2.dist-info/METADATA
test_PyRVC2-1.8.2.dist-info/WHEEL
test_PyRVC2-1.8.2.dist-info/top_level.txt
test_PyRVC2-1.8.2.dist-info/RECORD
